solvit/__init__.py
solvit/models.py
solvit/tests/__init__.py
solvit-0.0.2.dist-info/LICENSE
solvit-0.0.2.dist-info/METADATA
solvit-0.0.2.dist-info/WHEEL
solvit-0.0.2.dist-info/entry_points.txt
solvit-0.0.2.dist-info/top_level.txt
solvit-0.0.2.dist-info/RECORD
